README.txt
setup.py
docs/HISTORY.txt
upfront/__init__.py
upfront.foldercontents.egg-info/PKG-INFO
upfront.foldercontents.egg-info/SOURCES.txt
upfront.foldercontents.egg-info/dependency_links.txt
upfront.foldercontents.egg-info/entry_points.txt
upfront.foldercontents.egg-info/namespace_packages.txt
upfront.foldercontents.egg-info/not-zip-safe
upfront.foldercontents.egg-info/requires.txt
upfront.foldercontents.egg-info/top_level.txt
upfront/foldercontents/TODO.txt
upfront/foldercontents/__init__.py
upfront/foldercontents/adapters.py
upfront/foldercontents/configure.zcml
upfront/foldercontents/eventhandlers.py
upfront/foldercontents/foldercontents.py
upfront/foldercontents/interfaces.py
upfront/foldercontents/overrides.zcml
upfront/foldercontents/setuphandlers.py
upfront/foldercontents/version.txt
upfront/foldercontents/docs/__init__.py
upfront/foldercontents/docs/foldercontents.txt
upfront/foldercontents/tests/__init__.py
upfront/foldercontents/tests/test_doctests.py