Metadata-Version: 1.0
Name: upfront.foldercontents
Version: 1.0
Summary: A folder contents implementation for Plone that does not depend on the portal_catalog
Home-page: http://svn.plone.org/svn/collective/upfront.foldercontents
Author: Roché Compaan
Author-email: roche@upfrontsystems.co.za
License: GPL
Platform: UNKNOWN
Classifier: Programming Language :: Python
Classifier: Topic :: Software Development :: Libraries :: Python Modules
Classifier: Framework :: Zope2
Classifier: Framework :: Plone
